ScenicOverlook-0.3.0.dist-info/DESCRIPTION.rst
ScenicOverlook-0.3.0.dist-info/METADATA
ScenicOverlook-0.3.0.dist-info/RECORD
ScenicOverlook-0.3.0.dist-info/WHEEL
ScenicOverlook-0.3.0.dist-info/metadata.json
ScenicOverlook-0.3.0.dist-info/top_level.txt
scenicoverlook/__init__.py
