Metadata-Version: 2.0
Name: ScenicOverlook
Version: 0.3.0
Summary: A library for incremental, in-memory map-reduces
Home-page: https://github.com/pschanely/ScenicOverlook
Author: Phillip Schanely
Author-email: pschanely+vE7F@gmail.com
License: BSD (3 clause)
Keywords: algorithms datastructures
Platform: UNKNOWN
Classifier: Development Status :: 3 - Alpha
Classifier: Intended Audience :: Developers
Classifier: License :: OSI Approved :: BSD License
Classifier: Operating System :: OS Independent
Classifier: Topic :: Software Development :: Libraries
Classifier: Programming Language :: Python :: 2
Classifier: Programming Language :: Python :: 2.7
Classifier: Programming Language :: Python :: 3
Classifier: Programming Language :: Python :: 3.2
Classifier: Programming Language :: Python :: 3.3
Classifier: Programming Language :: Python :: 3.4
Classifier: Programming Language :: Python :: 3.5
Classifier: Programming Language :: Python :: 3.6
